{
  "uk-01": {
    "name": "Greater London",
    "region": "London",
    "centroid": [
      51.5074,
      -0.1278
    ],
    "la_codes": [
      "E09000001",
      "E09000002",
      "E09000003",
      "E09000004",
      "E09000005",
      "E09000006",
      "E09000007",
      "E09000008",
      "E09000009",
      "E09000010",
      "E09000011",
      "E09000012",
      "E09000013",
      "E09000014",
      "E09000015",
      "E09000016",
      "E09000017",
      "E09000018",
      "E09000019",
      "E09000020",
      "E09000021",
      "E09000022",
      "E09000023",
      "E09000024",
      "E09000025",
      "E09000026",
      "E09000027",
      "E09000028",
      "E09000029",
      "E09000030",
      "E09000031",
      "E09000032",
      "E09000033"
    ]
  },
  "uk-02": {
    "name": "Crawley",
    "region": "South East",
    "centroid": [
      51.1099,
      -0.1895
    ],
    "la_codes": [
      "E07000061"
    ]
  },
  "uk-03": {
    "name": "Reading",
    "region": "South East",
    "centroid": [
      51.4543,
      -0.9781
    ],
    "la_codes": [
      "E06000038"
    ]
  },
  "uk-04": {
    "name": "Maidstone",
    "region": "South East",
    "centroid": [
      51.272,
      0.5299
    ],
    "la_codes": [
      "E07000110"
    ]
  },
  "uk-05": {
    "name": "South Hampshire",
    "region": "South East",
    "centroid": [
      50.9097,
      -1.4044
    ],
    "la_codes": [
      "E06000044",
      "E06000045",
      "E07000086",
      "E07000087",
      "E07000088",
      "E07000090"
    ]
  },
  "uk-06": {
    "name": "Milton Keynes",
    "region": "South East",
    "centroid": [
      52.0406,
      -0.7594
    ],
    "la_codes": [
      "E06000042"
    ]
  },
  "uk-07": {
    "name": "Slough",
    "region": "South East",
    "centroid": [
      51.5105,
      -0.595
    ],
    "la_codes": [
      "E06000039"
    ]
  },
  "uk-08": {
    "name": "Hastings",
    "region": "South East",
    "centroid": [
      50.8543,
      0.573
    ],
    "la_codes": [
      "E07000064"
    ]
  },
  "uk-09": {
    "name": "High Wycombe",
    "region": "South East",
    "centroid": [
      51.6288,
      -0.7482
    ],
    "la_codes": [
      "E06000060"
    ]
  },
  "uk-10": {
    "name": "Basingstoke",
    "region": "South East",
    "centroid": [
      51.2667,
      -1.0876
    ],
    "la_codes": [
      "E07000084"
    ]
  },
  "uk-11": {
    "name": "Brighton & Hove",
    "region": "South East",
    "centroid": [
      50.8225,
      -0.1372
    ],
    "la_codes": [
      "E06000043"
    ]
  },
  "uk-12": {
    "name": "Medway Towns",
    "region": "South East",
    "centroid": [
      51.384,
      0.5229
    ],
    "la_codes": [
      "E06000035"
    ]
  },
  "uk-13": {
    "name": "Eastbourne",
    "region": "South East",
    "centroid": [
      50.7684,
      0.282
    ],
    "la_codes": [
      "E07000062"
    ]
  },
  "uk-14": {
    "name": "Farnborough/Aldershot",
    "region": "South East",
    "centroid": [
      51.2968,
      -0.7542
    ],
    "la_codes": [
      "E07000092"
    ]
  },
  "uk-15": {
    "name": "Oxford",
    "region": "South East",
    "centroid": [
      51.752,
      -1.2577
    ],
    "la_codes": [
      "E07000178"
    ]
  },
  "uk-16": {
    "name": "Thanet",
    "region": "South East",
    "centroid": [
      51.3814,
      1.3895
    ],
    "la_codes": [
      "E07000114"
    ]
  },
  "uk-17": {
    "name": "Norwich",
    "region": "East of England",
    "centroid": [
      52.6309,
      1.2974
    ],
    "la_codes": [
      "E07000148"
    ]
  },
  "uk-18": {
    "name": "Chelmsford",
    "region": "East of England",
    "centroid": [
      51.7361,
      0.4798
    ],
    "la_codes": [
      "E07000070"
    ]
  },
  "uk-19": {
    "name": "Peterborough",
    "region": "East of England",
    "centroid": [
      52.5695,
      -0.2405
    ],
    "la_codes": [
      "E06000031"
    ]
  },
  "uk-20": {
    "name": "Ipswich",
    "region": "East of England",
    "centroid": [
      52.0567,
      1.1482
    ],
    "la_codes": [
      "E07000202"
    ]
  },
  "uk-21": {
    "name": "Cambridge",
    "region": "East of England",
    "centroid": [
      52.2053,
      0.1218
    ],
    "la_codes": [
      "E07000008"
    ]
  },
  "uk-22": {
    "name": "Colchester",
    "region": "East of England",
    "centroid": [
      51.8959,
      0.8919
    ],
    "la_codes": [
      "E07000071"
    ]
  },
  "uk-23": {
    "name": "Bedford",
    "region": "East of England",
    "centroid": [
      52.1361,
      -0.4667
    ],
    "la_codes": [
      "E06000055"
    ]
  },
  "uk-24": {
    "name": "Luton",
    "region": "East of England",
    "centroid": [
      51.8787,
      -0.42
    ],
    "la_codes": [
      "E06000032"
    ]
  },
  "uk-25": {
    "name": "Basildon",
    "region": "East of England",
    "centroid": [
      51.5731,
      0.4906
    ],
    "la_codes": [
      "E07000066"
    ]
  },
  "uk-26": {
    "name": "Southend-on-Sea",
    "region": "East of England",
    "centroid": [
      51.5461,
      0.7077
    ],
    "la_codes": [
      "E06000033"
    ]
  },
  "uk-27": {
    "name": "Birmingham/Solihull",
    "region": "West Midlands",
    "centroid": [
      52.4862,
      -1.8904
    ],
    "la_codes": [
      "E08000025",
      "E08000029"
    ]
  },
  "uk-28": {
    "name": "Black Country",
    "region": "West Midlands",
    "centroid": [
      52.507,
      -2.05
    ],
    "la_codes": [
      "E08000027",
      "E08000028",
      "E08000030",
      "E08000031"
    ]
  },
  "uk-29": {
    "name": "Coventry",
    "region": "West Midlands",
    "centroid": [
      52.4068,
      -1.5197
    ],
    "la_codes": [
      "E08000026"
    ]
  },
  "uk-30": {
    "name": "Telford",
    "region": "West Midlands",
    "centroid": [
      52.6766,
      -2.4469
    ],
    "la_codes": [
      "E06000020"
    ]
  },
  "uk-31": {
    "name": "Leicester",
    "region": "East Midlands",
    "centroid": [
      52.6369,
      -1.1398
    ],
    "la_codes": [
      "E06000016"
    ]
  },
  "uk-32": {
    "name": "Northampton",
    "region": "East Midlands",
    "centroid": [
      52.2405,
      -0.9027
    ],
    "la_codes": [
      "E06000061"
    ]
  },
  "uk-33": {
    "name": "Derby",
    "region": "East Midlands",
    "centroid": [
      52.9226,
      -1.4746
    ],
    "la_codes": [
      "E06000015"
    ]
  },
  "uk-34": {
    "name": "Nottingham",
    "region": "East Midlands",
    "centroid": [
      52.9548,
      -1.1581
    ],
    "la_codes": [
      "E06000018"
    ]
  },
  "uk-35": {
    "name": "Stoke-on-Trent",
    "region": "East Midlands",
    "centroid": [
      53.0027,
      -2.1794
    ],
    "la_codes": [
      "E06000021"
    ]
  },
  "uk-36": {
    "name": "Chesterfield",
    "region": "East Midlands",
    "centroid": [
      53.235,
      -1.4209
    ],
    "la_codes": [
      "E07000034"
    ]
  },
  "uk-37": {
    "name": "Mansfield",
    "region": "East Midlands",
    "centroid": [
      53.1476,
      -1.195
    ],
    "la_codes": [
      "E07000174"
    ]
  },
  "uk-38": {
    "name": "Lincoln",
    "region": "East Midlands",
    "centroid": [
      53.2307,
      -0.5406
    ],
    "la_codes": [
      "E07000138"
    ]
  },
  "uk-39": {
    "name": "Burton-upon-Trent",
    "region": "East Midlands",
    "centroid": [
      52.8019,
      -1.6367
    ],
    "la_codes": [
      "E07000032"
    ]
  },
  "uk-40": {
    "name": "West Yorkshire (Leeds)",
    "region": "Yorkshire & Humber",
    "centroid": [
      53.7997,
      -1.5492
    ],
    "la_codes": [
      "E08000032",
      "E08000033",
      "E08000034",
      "E08000035",
      "E08000036"
    ]
  },
  "uk-41": {
    "name": "Sheffield",
    "region": "Yorkshire & Humber",
    "centroid": [
      53.3811,
      -1.4701
    ],
    "la_codes": [
      "E08000019",
      "E08000018"
    ]
  },
  "uk-42": {
    "name": "Grimsby",
    "region": "Yorkshire & Humber",
    "centroid": [
      53.5674,
      -0.0806
    ],
    "la_codes": [
      "E06000012"
    ]
  },
  "uk-43": {
    "name": "York",
    "region": "Yorkshire & Humber",
    "centroid": [
      53.959,
      -1.0815
    ],
    "la_codes": [
      "E06000014"
    ]
  },
  "uk-44": {
    "name": "Barnsley/Dearne Valley",
    "region": "Yorkshire & Humber",
    "centroid": [
      53.5527,
      -1.4797
    ],
    "la_codes": [
      "E08000016"
    ]
  },
  "uk-45": {
    "name": "Doncaster",
    "region": "Yorkshire & Humber",
    "centroid": [
      53.5228,
      -1.1285
    ],
    "la_codes": [
      "E08000017"
    ]
  },
  "uk-46": {
    "name": "Kingston upon Hull",
    "region": "Yorkshire & Humber",
    "centroid": [
      53.7457,
      -0.3367
    ],
    "la_codes": [
      "E06000010"
    ]
  },
  "uk-47": {
    "name": "Greater Manchester",
    "region": "North West",
    "centroid": [
      53.4808,
      -2.2426
    ],
    "la_codes": [
      "E08000001",
      "E08000002",
      "E08000003",
      "E08000004",
      "E08000005",
      "E08000006",
      "E08000007",
      "E08000008",
      "E08000009",
      "E08000010"
    ]
  },
  "uk-48": {
    "name": "Liverpool",
    "region": "North West",
    "centroid": [
      53.4084,
      -2.9916
    ],
    "la_codes": [
      "E08000011",
      "E08000012",
      "E08000014"
    ]
  },
  "uk-49": {
    "name": "Preston",
    "region": "North West",
    "centroid": [
      53.7632,
      -2.7031
    ],
    "la_codes": [
      "E07000123",
      "E07000126"
    ]
  },
  "uk-50": {
    "name": "Wigan",
    "region": "North West",
    "centroid": [
      53.5453,
      -2.6328
    ],
    "la_codes": [
      "E08000010"
    ]
  },
  "uk-51": {
    "name": "Burnley",
    "region": "North West",
    "centroid": [
      53.7895,
      -2.2374
    ],
    "la_codes": [
      "E07000117"
    ]
  },
  "uk-52": {
    "name": "Blackburn",
    "region": "North West",
    "centroid": [
      53.7481,
      -2.4817
    ],
    "la_codes": [
      "E06000008"
    ]
  },
  "uk-53": {
    "name": "Warrington",
    "region": "North West",
    "centroid": [
      53.39,
      -2.597
    ],
    "la_codes": [
      "E06000007"
    ]
  },
  "uk-54": {
    "name": "Accrington/Rossendale",
    "region": "North West",
    "centroid": [
      53.7534,
      -2.364
    ],
    "la_codes": [
      "E07000116",
      "E07000125"
    ]
  },
  "uk-55": {
    "name": "Blackpool",
    "region": "North West",
    "centroid": [
      53.8175,
      -3.0357
    ],
    "la_codes": [
      "E06000009"
    ]
  },
  "uk-56": {
    "name": "Birkenhead",
    "region": "North West",
    "centroid": [
      53.3933,
      -3.0146
    ],
    "la_codes": [
      "E08000015"
    ]
  },
  "uk-57": {
    "name": "Sunderland",
    "region": "North East",
    "centroid": [
      54.9069,
      -1.3838
    ],
    "la_codes": [
      "E08000024"
    ]
  },
  "uk-58": {
    "name": "Tyneside",
    "region": "North East",
    "centroid": [
      54.9783,
      -1.6178
    ],
    "la_codes": [
      "E08000021",
      "E08000022",
      "E08000023",
      "E08000037"
    ]
  },
  "uk-59": {
    "name": "Teesside",
    "region": "North East",
    "centroid": [
      54.5751,
      -1.2348
    ],
    "la_codes": [
      "E06000002",
      "E06000003",
      "E06000004"
    ]
  },
  "uk-60": {
    "name": "Bristol",
    "region": "South West",
    "centroid": [
      51.4545,
      -2.5879
    ],
    "la_codes": [
      "E06000023"
    ]
  },
  "uk-61": {
    "name": "Cheltenham",
    "region": "South West",
    "centroid": [
      51.8994,
      -2.0785
    ],
    "la_codes": [
      "E07000078"
    ]
  },
  "uk-62": {
    "name": "Bournemouth/Poole",
    "region": "South West",
    "centroid": [
      50.7192,
      -1.8808
    ],
    "la_codes": [
      "E06000058"
    ]
  },
  "uk-63": {
    "name": "Gloucester",
    "region": "South West",
    "centroid": [
      51.8642,
      -2.2382
    ],
    "la_codes": [
      "E07000081"
    ]
  },
  "uk-64": {
    "name": "Exeter",
    "region": "South West",
    "centroid": [
      50.7184,
      -3.5339
    ],
    "la_codes": [
      "E07000041"
    ]
  },
  "uk-65": {
    "name": "Plymouth",
    "region": "South West",
    "centroid": [
      50.3755,
      -4.1427
    ],
    "la_codes": [
      "E06000026"
    ]
  },
  "uk-66": {
    "name": "Swindon",
    "region": "South West",
    "centroid": [
      51.558,
      -1.7826
    ],
    "la_codes": [
      "E06000030"
    ]
  },
  "uk-67": {
    "name": "Torquay/Paignton",
    "region": "South West",
    "centroid": [
      50.4619,
      -3.5253
    ],
    "la_codes": [
      "E06000027"
    ]
  },
  "uk-68": {
    "name": "Cardiff",
    "region": "Wales",
    "centroid": [
      51.4816,
      -3.1791
    ],
    "la_codes": [
      "W06000015"
    ]
  },
  "uk-69": {
    "name": "Newport",
    "region": "Wales",
    "centroid": [
      51.5842,
      -2.9977
    ],
    "la_codes": [
      "W06000022"
    ]
  },
  "uk-70": {
    "name": "Swansea",
    "region": "Wales",
    "centroid": [
      51.6214,
      -3.9436
    ],
    "la_codes": [
      "W06000011"
    ]
  },
  "uk-71": {
    "name": "Greater Glasgow",
    "region": "Scotland",
    "centroid": [
      55.8642,
      -4.2518
    ],
    "la_codes": [
      "S12000049",
      "S12000038",
      "S12000039",
      "S12000044",
      "S12000045"
    ]
  },
  "uk-72": {
    "name": "Motherwell",
    "region": "Scotland",
    "centroid": [
      55.7928,
      -3.9954
    ],
    "la_codes": [
      "S12000044",
      "S12000029"
    ]
  },
  "uk-73": {
    "name": "Edinburgh",
    "region": "Scotland",
    "centroid": [
      55.9533,
      -3.1883
    ],
    "la_codes": [
      "S12000036"
    ]
  },
  "uk-74": {
    "name": "Aberdeen",
    "region": "Scotland",
    "centroid": [
      57.1497,
      -2.0943
    ],
    "la_codes": [
      "S12000033",
      "S12000034"
    ]
  },
  "uk-75": {
    "name": "Dundee",
    "region": "Scotland",
    "centroid": [
      56.462,
      -2.9707
    ],
    "la_codes": [
      "S12000042"
    ]
  }
}